README.rst
setup.py
msxf_flow_engine/__init__.py
msxf_flow_engine/agent.py
msxf_flow_engine/conversation.py
msxf_flow_engine/dispatcher.py
msxf_flow_engine/domain.py
msxf_flow_engine/featurizers.py
msxf_flow_engine/interpreter.py
msxf_flow_engine/processor.py
msxf_flow_engine/rasa_util.py
msxf_flow_engine/slots.py
msxf_flow_engine/tracker_store.py
msxf_flow_engine/trackers.py
msxf_flow_engine/utils.py
msxf_flow_engine/version.py
msxf_flow_engine.egg-info/PKG-INFO
msxf_flow_engine.egg-info/SOURCES.txt
msxf_flow_engine.egg-info/dependency_links.txt
msxf_flow_engine.egg-info/top_level.txt
msxf_flow_engine/actions/__init__.py
msxf_flow_engine/actions/action.py
msxf_flow_engine/actions/factories.py
msxf_flow_engine/actions/forms.py
msxf_flow_engine/channels/__init__.py
msxf_flow_engine/channels/channel.py
msxf_flow_engine/channels/console.py
msxf_flow_engine/channels/custom.py
msxf_flow_engine/channels/direct.py
msxf_flow_engine/channels/file.py
msxf_flow_engine/channels/mattermost.py
msxf_flow_engine/channels/rest.py
msxf_flow_engine/channels/slack.py
msxf_flow_engine/events/__init__.py
msxf_flow_engine/policies/__init__.py
msxf_flow_engine/policies/augmented_memoization.py
msxf_flow_engine/policies/ensemble.py
msxf_flow_engine/policies/fallback.py
msxf_flow_engine/policies/keras_policy.py
msxf_flow_engine/policies/memoization.py
msxf_flow_engine/policies/online_trainer.py
msxf_flow_engine/policies/policy.py
msxf_flow_engine/policies/sklearn_policy.py
msxf_flow_engine/training/__init__.py
msxf_flow_engine/training/data.py
msxf_flow_engine/training/dsl.py
msxf_flow_engine/training/generator.py
msxf_flow_engine/training/structures.py
msxf_flow_engine/training/visualization.py