Metadata-Version: 2.1
Name: msxf-flow-engine
Version: 0.2.1
Summary: Machine learning based dialogue engine for conversational software.
Home-page: UNKNOWN
Author: msxf
Author-email: 195832858@qq.com
Maintainer: msxf
Maintainer-email: 195832858@qq.com
License: Apache 2.0
Platform: UNKNOWN
Classifier: Development Status :: 4 - Beta
Classifier: Intended Audience :: Developers
Classifier: License :: OSI Approved :: Apache Software License
Classifier: Programming Language :: Python
Classifier: Programming Language :: Python :: 2.7
Classifier: Programming Language :: Python :: 3.5
Classifier: Programming Language :: Python :: 3.6
Classifier: Topic :: Software Development :: Libraries
